clovax/__init__.py
clovax/chat.py
clovax/clovax.py
clovax/constants.py
clovax/errors.py
clovax-0.0.6.dist-info/LICENSE
clovax-0.0.6.dist-info/METADATA
clovax-0.0.6.dist-info/WHEEL
clovax-0.0.6.dist-info/top_level.txt
clovax-0.0.6.dist-info/RECORD
