Metadata-Version: 2.1
Name: clovax
Version: 0.0.6
Summary: Unofficial CLOVA X API
Home-page: https://github.com/mirusu400/CLOVA-X-API
Author: mirusu400
Author-email: mirusu400@naver.com
Keywords: ClovaX,Naver,CLOVA,CLOVA X,CLOVA X API
Classifier: Programming Language :: Python :: 3.7
Classifier: Programming Language :: Python :: 3.8
Classifier: Programming Language :: Python :: 3.9
Classifier: Programming Language :: Python :: 3.10
Classifier: Programming Language :: Python :: 3.11
Requires-Python: >=3.7
License-File: LICENSE
Requires-Dist: requests
